convertme/__init__.py
convertme/cli.py
convertme/dataset.py
convertme/metadata.py
convertme/reader_interface.py
convertme/writer_interface.py
convertme/burmeister/__init__.py
convertme/burmeister/burmeister_reader.py
convertme/burmeister/burmeister_writer.py
convertme/cex/__init__.py
convertme/cex/cex_reader.py
convertme/cex/cex_writer.py
convertme/csv/__init__.py
convertme/csv/csv_reader.py
convertme/csv/csv_writer.py
convertme/fimi/__init__.py
convertme/fimi/fimi_reader.py
convertme/fimi/fimi_writer.py
convertme/matlab/__init__.py
convertme/matlab/matlab_reader.py
convertme/matlab/matlab_writer.py
convertme-0.1.2.dist-info/AUTHORS.rst
convertme-0.1.2.dist-info/LICENSE
convertme-0.1.2.dist-info/METADATA
convertme-0.1.2.dist-info/WHEEL
convertme-0.1.2.dist-info/entry_points.txt
convertme-0.1.2.dist-info/top_level.txt
convertme-0.1.2.dist-info/RECORD
