Metadata-Version: 2.1
Name: convertme
Version: 0.1.2
Summary: Simple dataset convertor in Python
Home-page: https://github.com/mikulatomas/convertme
Author: Radek Janoštík, Tomáš Mikula, Tomáš Urbanec, Roman Vyjídáček
Author-email: radek.janostik@upol.cz, mail@tomasmikula.cz, tomas.urbanec@upol.cz, r.vyjidacek@gmail.com
License: MIT license
Keywords: convertme
Platform: UNKNOWN
Classifier: Development Status :: 2 - Pre-Alpha
Classifier: Intended Audience :: Developers
Classifier: License :: OSI Approved :: MIT License
Classifier: Natural Language :: English
Classifier: Programming Language :: Python :: 3
Classifier: Programming Language :: Python :: 3.5
Classifier: Programming Language :: Python :: 3.6
Classifier: Programming Language :: Python :: 3.7
Classifier: Programming Language :: Python :: 3.8
Requires-Python: >=3.5
Requires-Dist: Click (>=7.0)
Requires-Dist: mat4py (>=0.4.3)
Requires-Dist: h5py (>=2.10.0)
Requires-Dist: bitarray (>=1.2.1)
Provides-Extra: docs
Requires-Dist: sphinx ; extra == 'docs'
